[
  {
    "_index": "otel-traces-2025-12-22",
    "_id": "KE-cQ5sBmc08HMcQxEAg",
    "_score": null,
    "_source": {
      "attributes": {
        "component": "proxy",
        "data_stream": {
          "dataset": "default",
          "namespace": "namespace",
          "type": "span"
        },
        "http.protocol": "HTTP/1.1",
        "http.status_code": "200",
        "peer.address": "172.22.0.6:4000",
        "response_flags": "-",
        "upstream_address": "172.22.0.6:4000",
        "upstream_cluster": "flagd-ui",
        "upstream_cluster.name": "flagd-ui"
      },
      "droppedAttributesCount": 0,
      "droppedEventsCount": 0,
      "droppedLinksCount": 0,
      "endTime": "2025-12-22T01:11:42.29606Z",
      "instrumentationScope": {
        "droppedAttributesCount": 0,
        "name": "envoy",
        "schemaUrl": "",
        "version": "6aa1dcf8663b46421a2b73b8c357c20769600e53/1.34.10/Clean/RELEASE/BoringSSL"
      },
      "kind": "Client",
      "name": "router flagd-ui egress",
      "parentSpanId": "47c7240b0636d630",
      "resource": {
        "host.name": "d2d8144cbe33",
        "os.type": "linux",
        "service.name": "frontend-proxy",
        "service.namespace": "opentelemetry-demo",
        "service.version": "2.1.3",
        "telemetry.sdk.language": "cpp",
        "telemetry.sdk.name": "envoy",
        "telemetry.sdk.version": "6aa1dcf8663b46421a2b73b8c357c20769600e53/1.34.10/Clean/RELEASE/BoringSSL"
      },
      "spanId": "70aa0b23fe6883c6",
      "startTime": "2025-12-22T01:11:32.293332Z",
      "status": {
        "code": "Unset",
        "message": ""
      },
      "@timestamp": "0001-01-01T00:00:00Z",
      "traceId": "3362b3cbb5a39752ae185cb3e4aa3e40",
      "traceState": ""
    },
    "sort": [
      1766365902296
    ]
  },
  {
    "_index": "otel-traces-2025-12-22",
    "_id": "KU-cQ5sBmc08HMcQxEAg",
    "_score": null,
    "_source": {
      "attributes": {
        "component": "proxy",
        "data_stream": {
          "dataset": "default",
          "namespace": "namespace",
          "type": "span"
        },
        "downstream_cluster": "-",
        "guid:x-request-id": "692cc01f-8d53-942a-b385-c78c4e9502ae",
        "http.method": "GET",
        "http.protocol": "HTTP/1.1",
        "http.status_code": "200",
        "http.url": "http://localhost:8080/featurelive/longpoll?_csrf_token=fDgHJjZ2YQUzNGFKRC4JZ0JoIksbXTk58kQbqEWTXkV-wFyQ4YprllSr&_track_static%5B0%5D=http%3A%2F%2Flocalhost%3A8080%2Ffeature%2Fassets%2Fcss%2Fapp-6f5d86242cf5220b8531adc7351da8bc.css%3Fvsn%3Dd&_track_static%5B1%5D=http%3A%2F%2Flo",
        "node_id": "",
        "peer.address": "172.22.0.1",
        "request_size": "0",
        "response_flags": "-",
        "response_size": "254",
        "upstream_cluster": "flagd-ui",
        "upstream_cluster.name": "flagd-ui",
        "user_agent": "Mozilla/5.0 (X11; Linux x86_64) AppleWebKit/537.36 (KHTML, like Gecko) Chrome/140.0.0.0 Safari/537.36",
        "zone": ""
      },
      "droppedAttributesCount": 0,
      "droppedEventsCount": 0,
      "droppedLinksCount": 0,
      "endTime": "2025-12-22T01:11:42.296121Z",
      "instrumentationScope": {
        "droppedAttributesCount": 0,
        "name": "envoy",
        "schemaUrl": "",
        "version": "6aa1dcf8663b46421a2b73b8c357c20769600e53/1.34.10/Clean/RELEASE/BoringSSL"
      },
      "kind": "Server",
      "name": "ingress",
      "parentSpanId": "",
      "resource": {
        "host.name": "d2d8144cbe33",
        "os.type": "linux",
        "service.name": "frontend-proxy",
        "service.namespace": "opentelemetry-demo",
        "service.version": "2.1.3",
        "telemetry.sdk.language": "cpp",
        "telemetry.sdk.name": "envoy",
        "telemetry.sdk.version": "6aa1dcf8663b46421a2b73b8c357c20769600e53/1.34.10/Clean/RELEASE/BoringSSL"
      },
      "spanId": "47c7240b0636d630",
      "startTime": "2025-12-22T01:11:32.293105Z",
      "status": {
        "code": "Unset",
        "message": ""
      },
      "@timestamp": "0001-01-01T00:00:00Z",
      "traceId": "3362b3cbb5a39752ae185cb3e4aa3e40",
      "traceState": ""
    },
    "sort": [
      1766365902296
    ]
  },
  {
    "_index": "otel-traces-2025-12-22",
    "_id": "JU-cQ5sBmc08HMcQu0Ba",
    "_score": null,
    "_source": {
      "attributes": {
        "client.address": "::ffff:172.22.0.12",
        "data_stream": {
          "dataset": "default",
          "namespace": "namespace",
          "type": "span"
        },
        "http.request.method": "GET",
        "http.response.status_code": 200,
        "network.peer.address": "::ffff:172.22.0.12",
        "network.peer.port": 50302,
        "network.protocol.version": "1.1",
        "server.address": "localhost",
        "server.port": 8080,
        "url.path": "/live/longpoll",
        "url.query": "_csrf_token=fDgHJjZ2YQUzNGFKRC4JZ0JoIksbXTk58kQbqEWTXkV-wFyQ4YprllSr&_track_static%5B0%5D=http%3A%2F%2Flocalhost%3A8080%2Ffeature%2Fassets%2Fcss%2Fapp-6f5d86242cf5220b8531adc7351da8bc.css%3Fvsn%3Dd&_track_static%5B1%5D=http%3A%2F%2Flocalhost%3A8080%2Ffeature%2Fassets%2Fjs%2Fapp-bfbcc471bc314daa4f94a55c88d5e19a.js%3Fvsn%3Dd&_mounts=0&_mount_attempts=0&_live_referer=undefined&vsn=2.0.0&token=SFMyNTY.g2gDaAR3AnYxbQAAABZQNUJZeXNucmJLM3lKS1JVTVVTSE1nWHcVZmxhZ2RfdWlAMTM4YjMzNjQwZjcyAAAOsgAAAABpR5wmbQAAACxwaHg6bHA6YVdDNGVrUzRBK3Q4UG91b0JHTXd4QT09MTc2NjM1NjY4MjcyMG4GAOEHEEObAWIAEnUA.vsDYiHMxefh9caXrXe9cKfj145Gy4oVImN4Sa1CQNy8",
        "url.scheme": "http",
        "user_agent.original": "Mozilla/5.0 (X11; Linux x86_64) AppleWebKit/537.36 (KHTML, like Gecko) Chrome/140.0.0.0 Safari/537.36"
      },
      "droppedAttributesCount": 0,
      "droppedEventsCount": 0,
      "droppedLinksCount": 0,
      "endTime": "2025-12-22T01:11:42.295795792Z",
      "instrumentationScope": {
        "droppedAttributesCount": 0,
        "name": "opentelemetry_bandit",
        "schemaUrl": "",
        "version": "0.3.0"
      },
      "kind": "Server",
      "name": "GET",
      "parentSpanId": "70aa0b23fe6883c6",
      "resource": {
        "host.name": "d2d8144cbe33",
        "os.type": "linux",
        "process.executable.name": "flagd_ui",
        "process.runtime.description": "Erlang/OTP 28 erts-16.0.2",
        "process.runtime.name": "BEAM",
        "process.runtime.version": "16.0.2",
        "service.instance.id": "flagd_ui@138b33640f72",
        "service.name": "flagd-ui",
        "service.namespace": "opentelemetry-demo",
        "service.version": "2.1.3",
        "telemetry.sdk.language": "erlang",
        "telemetry.sdk.name": "opentelemetry",
        "telemetry.sdk.version": "1.7.0"
      },
      "spanId": "7b0f196f2dfdda7f",
      "startTime": "2025-12-22T01:11:32.294016588Z",
      "status": {
        "code": "Unset",
        "message": ""
      },
      "@timestamp": "0001-01-01T00:00:00Z",
      "traceId": "3362b3cbb5a39752ae185cb3e4aa3e40",
      "traceState": ""
    },
    "sort": [
      1766365902295
    ]
  },
  {
    "_index": "otel-traces-2025-12-22",
    "_id": "I0-cQ5sBmc08HMcQtECD",
    "_score": null,
    "_source": {
      "attributes": {
        "data_stream": {
          "dataset": "default",
          "namespace": "namespace",
          "type": "span"
        },
        "http.flavor": "1.1",
        "http.method": "GET",
        "http.request_content_length": 0,
        "http.response_content_length": 100,
        "http.route": "/status",
        "http.scheme": "http",
        "http.status_code": 200,
        "http.target": "/status",
        "http.user_agent": "Go-http-client/1.1",
        "net.host.name": "_",
        "net.host.port": 8081,
        "net.sock.peer.addr": "172.22.0.27",
        "net.sock.peer.port": 55298
      },
      "droppedAttributesCount": 0,
      "droppedEventsCount": 0,
      "droppedLinksCount": 0,
      "endTime": "2025-12-22T01:11:40.533Z",
      "instrumentationScope": {
        "droppedAttributesCount": 0,
        "name": "nginx",
        "schemaUrl": "",
        "version": "1.29.0"
      },
      "kind": "Server",
      "name": "image-provider",
      "parentSpanId": "",
      "resource": {
        "host.name": "d2d8144cbe33",
        "os.type": "linux",
        "service.name": "image-provider"
      },
      "spanId": "abeaf37caaf81592",
      "startTime": "2025-12-22T01:11:40.533Z",
      "status": {
        "code": "Unset",
        "message": ""
      },
      "@timestamp": "0001-01-01T00:00:00Z",
      "traceId": "79a069330276046d2509d2caf1f00300",
      "traceState": ""
    },
    "sort": [
      1766365900533
    ]
  },
  {
    "_index": "otel-traces-2025-12-22",
    "_id": "Hk-cQ5sBmc08HMcQnUAO",
    "_score": null,
    "_source": {
      "attributes": {
        "component": "proxy",
        "data_stream": {
          "dataset": "default",
          "namespace": "namespace",
          "type": "span"
        },
        "http.protocol": "HTTP/1.1",
        "http.status_code": "200",
        "peer.address": "172.22.0.6:4000",
        "response_flags": "-",
        "upstream_address": "172.22.0.6:4000",
        "upstream_cluster": "flagd-ui",
        "upstream_cluster.name": "flagd-ui"
      },
      "droppedAttributesCount": 0,
      "droppedEventsCount": 0,
      "droppedLinksCount": 0,
      "endTime": "2025-12-22T01:11:32.284052Z",
      "instrumentationScope": {
        "droppedAttributesCount": 0,
        "name": "envoy",
        "schemaUrl": "",
        "version": "6aa1dcf8663b46421a2b73b8c357c20769600e53/1.34.10/Clean/RELEASE/BoringSSL"
      },
      "kind": "Client",
      "name": "router flagd-ui egress",
      "parentSpanId": "57bcef37b267f3ed",
      "resource": {
        "host.name": "d2d8144cbe33",
        "os.type": "linux",
        "service.name": "frontend-proxy",
        "service.namespace": "opentelemetry-demo",
        "service.version": "2.1.3",
        "telemetry.sdk.language": "cpp",
        "telemetry.sdk.name": "envoy",
        "telemetry.sdk.version": "6aa1dcf8663b46421a2b73b8c357c20769600e53/1.34.10/Clean/RELEASE/BoringSSL"
      },
      "spanId": "a316beff1f6881fe",
      "startTime": "2025-12-22T01:11:22.281545Z",
      "status": {
        "code": "Unset",
        "message": ""
      },
      "@timestamp": "0001-01-01T00:00:00Z",
      "traceId": "7905b79cddd448cb969d4dd63a0ba7e9",
      "traceState": ""
    },
    "sort": [
      1766365892284
    ]
  },
  {
    "_index": "otel-traces-2025-12-22",
    "_id": "H0-cQ5sBmc08HMcQnUAO",
    "_score": null,
    "_source": {
      "attributes": {
        "component": "proxy",
        "data_stream": {
          "dataset": "default",
          "namespace": "namespace",
          "type": "span"
        },
        "downstream_cluster": "-",
        "guid:x-request-id": "27753288-3356-9e45-8dc3-95c3946842ca",
        "http.method": "GET",
        "http.protocol": "HTTP/1.1",
        "http.status_code": "200",
        "http.url": "http://localhost:8080/featurelive/longpoll?_csrf_token=fDgHJjZ2YQUzNGFKRC4JZ0JoIksbXTk58kQbqEWTXkV-wFyQ4YprllSr&_track_static%5B0%5D=http%3A%2F%2Flocalhost%3A8080%2Ffeature%2Fassets%2Fcss%2Fapp-6f5d86242cf5220b8531adc7351da8bc.css%3Fvsn%3Dd&_track_static%5B1%5D=http%3A%2F%2Flo",
        "node_id": "",
        "peer.address": "172.22.0.1",
        "request_size": "0",
        "response_flags": "-",
        "response_size": "254",
        "upstream_cluster": "flagd-ui",
        "upstream_cluster.name": "flagd-ui",
        "user_agent": "Mozilla/5.0 (X11; Linux x86_64) AppleWebKit/537.36 (KHTML, like Gecko) Chrome/140.0.0.0 Safari/537.36",
        "zone": ""
      },
      "droppedAttributesCount": 0,
      "droppedEventsCount": 0,
      "droppedLinksCount": 0,
      "endTime": "2025-12-22T01:11:32.284119Z",
      "instrumentationScope": {
        "droppedAttributesCount": 0,
        "name": "envoy",
        "schemaUrl": "",
        "version": "6aa1dcf8663b46421a2b73b8c357c20769600e53/1.34.10/Clean/RELEASE/BoringSSL"
      },
      "kind": "Server",
      "name": "ingress",
      "parentSpanId": "",
      "resource": {
        "host.name": "d2d8144cbe33",
        "os.type": "linux",
        "service.name": "frontend-proxy",
        "service.namespace": "opentelemetry-demo",
        "service.version": "2.1.3",
        "telemetry.sdk.language": "cpp",
        "telemetry.sdk.name": "envoy",
        "telemetry.sdk.version": "6aa1dcf8663b46421a2b73b8c357c20769600e53/1.34.10/Clean/RELEASE/BoringSSL"
      },
      "spanId": "57bcef37b267f3ed",
      "startTime": "2025-12-22T01:11:22.281284Z",
      "status": {
        "code": "Unset",
        "message": ""
      },
      "@timestamp": "0001-01-01T00:00:00Z",
      "traceId": "7905b79cddd448cb969d4dd63a0ba7e9",
      "traceState": ""
    },
    "sort": [
      1766365892284
    ]
  },
  {
    "_index": "otel-traces-2025-12-22",
    "_id": "G0-cQ5sBmc08HMcQlEBE",
    "_score": null,
    "_source": {
      "attributes": {
        "client.address": "::ffff:172.22.0.12",
        "data_stream": {
          "dataset": "default",
          "namespace": "namespace",
          "type": "span"
        },
        "http.request.method": "GET",
        "http.response.status_code": 200,
        "network.peer.address": "::ffff:172.22.0.12",
        "network.peer.port": 50302,
        "network.protocol.version": "1.1",
        "server.address": "localhost",
        "server.port": 8080,
        "url.path": "/live/longpoll",
        "url.query": "_csrf_token=fDgHJjZ2YQUzNGFKRC4JZ0JoIksbXTk58kQbqEWTXkV-wFyQ4YprllSr&_track_static%5B0%5D=http%3A%2F%2Flocalhost%3A8080%2Ffeature%2Fassets%2Fcss%2Fapp-6f5d86242cf5220b8531adc7351da8bc.css%3Fvsn%3Dd&_track_static%5B1%5D=http%3A%2F%2Flocalhost%3A8080%2Ffeature%2Fassets%2Fjs%2Fapp-bfbcc471bc314daa4f94a55c88d5e19a.js%3Fvsn%3Dd&_mounts=0&_mount_attempts=0&_live_referer=undefined&vsn=2.0.0&token=SFMyNTY.g2gDaAR3AnYxbQAAABZQNUJZeXNucmJLM3lKS1JVTVVTSE1nWHcVZmxhZ2RfdWlAMTM4YjMzNjQwZjcyAAAOsgAAAABpR5wmbQAAACxwaHg6bHA6YVdDNGVrUzRBK3Q4UG91b0JHTXd4QT09MTc2NjM1NjY4MjcyMG4GAOEHEEObAWIAEnUA.vsDYiHMxefh9caXrXe9cKfj145Gy4oVImN4Sa1CQNy8",
        "url.scheme": "http",
        "user_agent.original": "Mozilla/5.0 (X11; Linux x86_64) AppleWebKit/537.36 (KHTML, like Gecko) Chrome/140.0.0.0 Safari/537.36"
      },
      "droppedAttributesCount": 0,
      "droppedEventsCount": 0,
      "droppedLinksCount": 0,
      "endTime": "2025-12-22T01:11:32.283772611Z",
      "instrumentationScope": {
        "droppedAttributesCount": 0,
        "name": "opentelemetry_bandit",
        "schemaUrl": "",
        "version": "0.3.0"
      },
      "kind": "Server",
      "name": "GET",
      "parentSpanId": "a316beff1f6881fe",
      "resource": {
        "host.name": "d2d8144cbe33",
        "os.type": "linux",
        "process.executable.name": "flagd_ui",
        "process.runtime.description": "Erlang/OTP 28 erts-16.0.2",
        "process.runtime.name": "BEAM",
        "process.runtime.version": "16.0.2",
        "service.instance.id": "flagd_ui@138b33640f72",
        "service.name": "flagd-ui",
        "service.namespace": "opentelemetry-demo",
        "service.version": "2.1.3",
        "telemetry.sdk.language": "erlang",
        "telemetry.sdk.name": "opentelemetry",
        "telemetry.sdk.version": "1.7.0"
      },
      "spanId": "0d1ad7cbca1a6e86",
      "startTime": "2025-12-22T01:11:22.282294094Z",
      "status": {
        "code": "Unset",
        "message": ""
      },
      "@timestamp": "0001-01-01T00:00:00Z",
      "traceId": "7905b79cddd448cb969d4dd63a0ba7e9",
      "traceState": ""
    },
    "sort": [
      1766365892283
    ]
  },
  {
    "_index": "otel-traces-2025-12-22",
    "_id": "Fk-cQ5sBmc08HMcQjUBu",
    "_score": null,
    "_source": {
      "attributes": {
        "data_stream": {
          "dataset": "default",
          "namespace": "namespace",
          "type": "span"
        },
        "http.flavor": "1.1",
        "http.method": "GET",
        "http.request_content_length": 0,
        "http.response_content_length": 100,
        "http.route": "/status",
        "http.scheme": "http",
        "http.status_code": 200,
        "http.target": "/status",
        "http.user_agent": "Go-http-client/1.1",
        "net.host.name": "_",
        "net.host.port": 8081,
        "net.sock.peer.addr": "172.22.0.27",
        "net.sock.peer.port": 55298
      },
      "droppedAttributesCount": 0,
      "droppedEventsCount": 0,
      "droppedLinksCount": 0,
      "endTime": "2025-12-22T01:11:30.533Z",
      "instrumentationScope": {
        "droppedAttributesCount": 0,
        "name": "nginx",
        "schemaUrl": "",
        "version": "1.29.0"
      },
      "kind": "Server",
      "name": "image-provider",
      "parentSpanId": "",
      "resource": {
        "host.name": "d2d8144cbe33",
        "os.type": "linux",
        "service.name": "image-provider"
      },
      "spanId": "4ff8ad0a8c280643",
      "startTime": "2025-12-22T01:11:30.533Z",
      "status": {
        "code": "Unset",
        "message": ""
      },
      "@timestamp": "0001-01-01T00:00:00Z",
      "traceId": "0f285c386a57c7177b1c76f56bd0fa0f",
      "traceState": ""
    },
    "sort": [
      1766365890533
    ]
  },
  {
    "_index": "otel-traces-2025-12-22",
    "_id": "9U-cQ5sBmc08HMcQdj8A",
    "_score": null,
    "_source": {
      "attributes": {
        "component": "proxy",
        "data_stream": {
          "dataset": "default",
          "namespace": "namespace",
          "type": "span"
        },
        "http.protocol": "HTTP/1.1",
        "http.status_code": "200",
        "peer.address": "172.22.0.6:4000",
        "response_flags": "-",
        "upstream_address": "172.22.0.6:4000",
        "upstream_cluster": "flagd-ui",
        "upstream_cluster.name": "flagd-ui"
      },
      "droppedAttributesCount": 0,
      "droppedEventsCount": 0,
      "droppedLinksCount": 0,
      "endTime": "2025-12-22T01:11:22.272041Z",
      "instrumentationScope": {
        "droppedAttributesCount": 0,
        "name": "envoy",
        "schemaUrl": "",
        "version": "6aa1dcf8663b46421a2b73b8c357c20769600e53/1.34.10/Clean/RELEASE/BoringSSL"
      },
      "kind": "Client",
      "name": "router flagd-ui egress",
      "parentSpanId": "03aebb2a3d3ba81e",
      "resource": {
        "host.name": "d2d8144cbe33",
        "os.type": "linux",
        "service.name": "frontend-proxy",
        "service.namespace": "opentelemetry-demo",
        "service.version": "2.1.3",
        "telemetry.sdk.language": "cpp",
        "telemetry.sdk.name": "envoy",
        "telemetry.sdk.version": "6aa1dcf8663b46421a2b73b8c357c20769600e53/1.34.10/Clean/RELEASE/BoringSSL"
      },
      "spanId": "98b1e52e0be349cb",
      "startTime": "2025-12-22T01:11:12.26951Z",
      "status": {
        "code": "Unset",
        "message": ""
      },
      "@timestamp": "0001-01-01T00:00:00Z",
      "traceId": "b0dac01ac4cdc552ae5fe992fb31af5a",
      "traceState": ""
    },
    "sort": [
      1766365882272
    ]
  },
  {
    "_index": "otel-traces-2025-12-22",
    "_id": "9k-cQ5sBmc08HMcQdj8A",
    "_score": null,
    "_source": {
      "attributes": {
        "component": "proxy",
        "data_stream": {
          "dataset": "default",
          "namespace": "namespace",
          "type": "span"
        },
        "downstream_cluster": "-",
        "guid:x-request-id": "2caac17e-7bd2-9444-8040-f0ceaac6c6b2",
        "http.method": "GET",
        "http.protocol": "HTTP/1.1",
        "http.status_code": "200",
        "http.url": "http://localhost:8080/featurelive/longpoll?_csrf_token=fDgHJjZ2YQUzNGFKRC4JZ0JoIksbXTk58kQbqEWTXkV-wFyQ4YprllSr&_track_static%5B0%5D=http%3A%2F%2Flocalhost%3A8080%2Ffeature%2Fassets%2Fcss%2Fapp-6f5d86242cf5220b8531adc7351da8bc.css%3Fvsn%3Dd&_track_static%5B1%5D=http%3A%2F%2Flo",
        "node_id": "",
        "peer.address": "172.22.0.1",
        "request_size": "0",
        "response_flags": "-",
        "response_size": "254",
        "upstream_cluster": "flagd-ui",
        "upstream_cluster.name": "flagd-ui",
        "user_agent": "Mozilla/5.0 (X11; Linux x86_64) AppleWebKit/537.36 (KHTML, like Gecko) Chrome/140.0.0.0 Safari/537.36",
        "zone": ""
      },
      "droppedAttributesCount": 0,
      "droppedEventsCount": 0,
      "droppedLinksCount": 0,
      "endTime": "2025-12-22T01:11:22.272103Z",
      "instrumentationScope": {
        "droppedAttributesCount": 0,
        "name": "envoy",
        "schemaUrl": "",
        "version": "6aa1dcf8663b46421a2b73b8c357c20769600e53/1.34.10/Clean/RELEASE/BoringSSL"
      },
      "kind": "Server",
      "name": "ingress",
      "parentSpanId": "",
      "resource": {
        "host.name": "d2d8144cbe33",
        "os.type": "linux",
        "service.name": "frontend-proxy",
        "service.namespace": "opentelemetry-demo",
        "service.version": "2.1.3",
        "telemetry.sdk.language": "cpp",
        "telemetry.sdk.name": "envoy",
        "telemetry.sdk.version": "6aa1dcf8663b46421a2b73b8c357c20769600e53/1.34.10/Clean/RELEASE/BoringSSL"
      },
      "spanId": "03aebb2a3d3ba81e",
      "startTime": "2025-12-22T01:11:12.269274Z",
      "status": {
        "code": "Unset",
        "message": ""
      },
      "@timestamp": "0001-01-01T00:00:00Z",
      "traceId": "b0dac01ac4cdc552ae5fe992fb31af5a",
      "traceState": ""
    },
    "sort": [
      1766365882272
    ]
  },
  {
    "_index": "otel-traces-2025-12-22",
    "_id": "8U-cQ5sBmc08HMcQbT8y",
    "_score": null,
    "_source": {
      "attributes": {
        "client.address": "::ffff:172.22.0.12",
        "data_stream": {
          "dataset": "default",
          "namespace": "namespace",
          "type": "span"
        },
        "http.request.method": "GET",
        "http.response.status_code": 200,
        "network.peer.address": "::ffff:172.22.0.12",
        "network.peer.port": 50302,
        "network.protocol.version": "1.1",
        "server.address": "localhost",
        "server.port": 8080,
        "url.path": "/live/longpoll",
        "url.query": "_csrf_token=fDgHJjZ2YQUzNGFKRC4JZ0JoIksbXTk58kQbqEWTXkV-wFyQ4YprllSr&_track_static%5B0%5D=http%3A%2F%2Flocalhost%3A8080%2Ffeature%2Fassets%2Fcss%2Fapp-6f5d86242cf5220b8531adc7351da8bc.css%3Fvsn%3Dd&_track_static%5B1%5D=http%3A%2F%2Flocalhost%3A8080%2Ffeature%2Fassets%2Fjs%2Fapp-bfbcc471bc314daa4f94a55c88d5e19a.js%3Fvsn%3Dd&_mounts=0&_mount_attempts=0&_live_referer=undefined&vsn=2.0.0&token=SFMyNTY.g2gDaAR3AnYxbQAAABZQNUJZeXNucmJLM3lKS1JVTVVTSE1nWHcVZmxhZ2RfdWlAMTM4YjMzNjQwZjcyAAAOsgAAAABpR5wmbQAAACxwaHg6bHA6YVdDNGVrUzRBK3Q4UG91b0JHTXd4QT09MTc2NjM1NjY4MjcyMG4GAOEHEEObAWIAEnUA.vsDYiHMxefh9caXrXe9cKfj145Gy4oVImN4Sa1CQNy8",
        "url.scheme": "http",
        "user_agent.original": "Mozilla/5.0 (X11; Linux x86_64) AppleWebKit/537.36 (KHTML, like Gecko) Chrome/140.0.0.0 Safari/537.36"
      },
      "droppedAttributesCount": 0,
      "droppedEventsCount": 0,
      "droppedLinksCount": 0,
      "endTime": "2025-12-22T01:11:22.271778039Z",
      "instrumentationScope": {
        "droppedAttributesCount": 0,
        "name": "opentelemetry_bandit",
        "schemaUrl": "",
        "version": "0.3.0"
      },
      "kind": "Server",
      "name": "GET",
      "parentSpanId": "98b1e52e0be349cb",
      "resource": {
        "host.name": "d2d8144cbe33",
        "os.type": "linux",
        "process.executable.name": "flagd_ui",
        "process.runtime.description": "Erlang/OTP 28 erts-16.0.2",
        "process.runtime.name": "BEAM",
        "process.runtime.version": "16.0.2",
        "service.instance.id": "flagd_ui@138b33640f72",
        "service.name": "flagd-ui",
        "service.namespace": "opentelemetry-demo",
        "service.version": "2.1.3",
        "telemetry.sdk.language": "erlang",
        "telemetry.sdk.name": "opentelemetry",
        "telemetry.sdk.version": "1.7.0"
      },
      "spanId": "d6249a03c5300212",
      "startTime": "2025-12-22T01:11:12.270193126Z",
      "status": {
        "code": "Unset",
        "message": ""
      },
      "@timestamp": "0001-01-01T00:00:00Z",
      "traceId": "b0dac01ac4cdc552ae5fe992fb31af5a",
      "traceState": ""
    },
    "sort": [
      1766365882271
    ]
  },
  {
    "_index": "otel-traces-2025-12-22",
    "_id": "70-cQ5sBmc08HMcQZj9V",
    "_score": null,
    "_source": {
      "attributes": {
        "data_stream": {
          "dataset": "default",
          "namespace": "namespace",
          "type": "span"
        },
        "http.flavor": "1.1",
        "http.method": "GET",
        "http.request_content_length": 0,
        "http.response_content_length": 100,
        "http.route": "/status",
        "http.scheme": "http",
        "http.status_code": 200,
        "http.target": "/status",
        "http.user_agent": "Go-http-client/1.1",
        "net.host.name": "_",
        "net.host.port": 8081,
        "net.sock.peer.addr": "172.22.0.27",
        "net.sock.peer.port": 55298
      },
      "droppedAttributesCount": 0,
      "droppedEventsCount": 0,
      "droppedLinksCount": 0,
      "endTime": "2025-12-22T01:11:20.533Z",
      "instrumentationScope": {
        "droppedAttributesCount": 0,
        "name": "nginx",
        "schemaUrl": "",
        "version": "1.29.0"
      },
      "kind": "Server",
      "name": "image-provider",
      "parentSpanId": "",
      "resource": {
        "host.name": "d2d8144cbe33",
        "os.type": "linux",
        "service.name": "image-provider"
      },
      "spanId": "94f0f448a5fda92a",
      "startTime": "2025-12-22T01:11:20.533Z",
      "status": {
        "code": "Unset",
        "message": ""
      },
      "@timestamp": "0001-01-01T00:00:00Z",
      "traceId": "fcf99d8843833dffca2effc51dbdc343",
      "traceState": ""
    },
    "sort": [
      1766365880533
    ]
  },
  {
    "_index": "otel-traces-2025-12-22",
    "_id": "5k-cQ5sBmc08HMcQRj8e",
    "_score": null,
    "_source": {
      "attributes": {
        "client.address": "::ffff:172.22.0.12",
        "data_stream": {
          "dataset": "default",
          "namespace": "namespace",
          "type": "span"
        },
        "http.request.method": "GET",
        "http.response.status_code": 200,
        "network.peer.address": "::ffff:172.22.0.12",
        "network.peer.port": 50302,
        "network.protocol.version": "1.1",
        "server.address": "localhost",
        "server.port": 8080,
        "url.path": "/live/longpoll",
        "url.query": "_csrf_token=fDgHJjZ2YQUzNGFKRC4JZ0JoIksbXTk58kQbqEWTXkV-wFyQ4YprllSr&_track_static%5B0%5D=http%3A%2F%2Flocalhost%3A8080%2Ffeature%2Fassets%2Fcss%2Fapp-6f5d86242cf5220b8531adc7351da8bc.css%3Fvsn%3Dd&_track_static%5B1%5D=http%3A%2F%2Flocalhost%3A8080%2Ffeature%2Fassets%2Fjs%2Fapp-bfbcc471bc314daa4f94a55c88d5e19a.js%3Fvsn%3Dd&_mounts=0&_mount_attempts=0&_live_referer=undefined&vsn=2.0.0&token=SFMyNTY.g2gDaAR3AnYxbQAAABZQNUJZeXNucmJLM3lKS1JVTVVTSE1nWHcVZmxhZ2RfdWlAMTM4YjMzNjQwZjcyAAAOsgAAAABpR5wmbQAAACxwaHg6bHA6YVdDNGVrUzRBK3Q4UG91b0JHTXd4QT09MTc2NjM1NjY4MjcyMG4GAOEHEEObAWIAEnUA.vsDYiHMxefh9caXrXe9cKfj145Gy4oVImN4Sa1CQNy8",
        "url.scheme": "http",
        "user_agent.original": "Mozilla/5.0 (X11; Linux x86_64) AppleWebKit/537.36 (KHTML, like Gecko) Chrome/140.0.0.0 Safari/537.36"
      },
      "droppedAttributesCount": 0,
      "droppedEventsCount": 0,
      "droppedLinksCount": 0,
      "endTime": "2025-12-22T01:11:12.259586234Z",
      "instrumentationScope": {
        "droppedAttributesCount": 0,
        "name": "opentelemetry_bandit",
        "schemaUrl": "",
        "version": "0.3.0"
      },
      "kind": "Server",
      "name": "GET",
      "parentSpanId": "5ae2edd00a843aeb",
      "resource": {
        "host.name": "d2d8144cbe33",
        "os.type": "linux",
        "process.executable.name": "flagd_ui",
        "process.runtime.description": "Erlang/OTP 28 erts-16.0.2",
        "process.runtime.name": "BEAM",
        "process.runtime.version": "16.0.2",
        "service.instance.id": "flagd_ui@138b33640f72",
        "service.name": "flagd-ui",
        "service.namespace": "opentelemetry-demo",
        "service.version": "2.1.3",
        "telemetry.sdk.language": "erlang",
        "telemetry.sdk.name": "opentelemetry",
        "telemetry.sdk.version": "1.7.0"
      },
      "spanId": "78d9c668e9d0ce98",
      "startTime": "2025-12-22T01:11:02.258061549Z",
      "status": {
        "code": "Unset",
        "message": ""
      },
      "@timestamp": "0001-01-01T00:00:00Z",
      "traceId": "69af90a71e3c9c849c12771789b860e6",
      "traceState": ""
    },
    "sort": [
      1766365872259
    ]
  },
  {
    "_index": "otel-traces-2025-12-22",
    "_id": "6U-cQ5sBmc08HMcQTj_u",
    "_score": null,
    "_source": {
      "attributes": {
        "component": "proxy",
        "data_stream": {
          "dataset": "default",
          "namespace": "namespace",
          "type": "span"
        },
        "http.protocol": "HTTP/1.1",
        "http.status_code": "200",
        "peer.address": "172.22.0.6:4000",
        "response_flags": "-",
        "upstream_address": "172.22.0.6:4000",
        "upstream_cluster": "flagd-ui",
        "upstream_cluster.name": "flagd-ui"
      },
      "droppedAttributesCount": 0,
      "droppedEventsCount": 0,
      "droppedLinksCount": 0,
      "endTime": "2025-12-22T01:11:12.259829Z",
      "instrumentationScope": {
        "droppedAttributesCount": 0,
        "name": "envoy",
        "schemaUrl": "",
        "version": "6aa1dcf8663b46421a2b73b8c357c20769600e53/1.34.10/Clean/RELEASE/BoringSSL"
      },
      "kind": "Client",
      "name": "router flagd-ui egress",
      "parentSpanId": "0991001b62039324",
      "resource": {
        "host.name": "d2d8144cbe33",
        "os.type": "linux",
        "service.name": "frontend-proxy",
        "service.namespace": "opentelemetry-demo",
        "service.version": "2.1.3",
        "telemetry.sdk.language": "cpp",
        "telemetry.sdk.name": "envoy",
        "telemetry.sdk.version": "6aa1dcf8663b46421a2b73b8c357c20769600e53/1.34.10/Clean/RELEASE/BoringSSL"
      },
      "spanId": "5ae2edd00a843aeb",
      "startTime": "2025-12-22T01:11:02.257388Z",
      "status": {
        "code": "Unset",
        "message": ""
      },
      "@timestamp": "0001-01-01T00:00:00Z",
      "traceId": "69af90a71e3c9c849c12771789b860e6",
      "traceState": ""
    },
    "sort": [
      1766365872259
    ]
  },
  {
    "_index": "otel-traces-2025-12-22",
    "_id": "6k-cQ5sBmc08HMcQTj_u",
    "_score": null,
    "_source": {
      "attributes": {
        "component": "proxy",
        "data_stream": {
          "dataset": "default",
          "namespace": "namespace",
          "type": "span"
        },
        "downstream_cluster": "-",
        "guid:x-request-id": "d91fcb2b-2b76-9da0-a993-cc9904f7dce1",
        "http.method": "GET",
        "http.protocol": "HTTP/1.1",
        "http.status_code": "200",
        "http.url": "http://localhost:8080/featurelive/longpoll?_csrf_token=fDgHJjZ2YQUzNGFKRC4JZ0JoIksbXTk58kQbqEWTXkV-wFyQ4YprllSr&_track_static%5B0%5D=http%3A%2F%2Flocalhost%3A8080%2Ffeature%2Fassets%2Fcss%2Fapp-6f5d86242cf5220b8531adc7351da8bc.css%3Fvsn%3Dd&_track_static%5B1%5D=http%3A%2F%2Flo",
        "node_id": "",
        "peer.address": "172.22.0.1",
        "request_size": "0",
        "response_flags": "-",
        "response_size": "254",
        "upstream_cluster": "flagd-ui",
        "upstream_cluster.name": "flagd-ui",
        "user_agent": "Mozilla/5.0 (X11; Linux x86_64) AppleWebKit/537.36 (KHTML, like Gecko) Chrome/140.0.0.0 Safari/537.36",
        "zone": ""
      },
      "droppedAttributesCount": 0,
      "droppedEventsCount": 0,
      "droppedLinksCount": 0,
      "endTime": "2025-12-22T01:11:12.259887Z",
      "instrumentationScope": {
        "droppedAttributesCount": 0,
        "name": "envoy",
        "schemaUrl": "",
        "version": "6aa1dcf8663b46421a2b73b8c357c20769600e53/1.34.10/Clean/RELEASE/BoringSSL"
      },
      "kind": "Server",
      "name": "ingress",
      "parentSpanId": "",
      "resource": {
        "host.name": "d2d8144cbe33",
        "os.type": "linux",
        "service.name": "frontend-proxy",
        "service.namespace": "opentelemetry-demo",
        "service.version": "2.1.3",
        "telemetry.sdk.language": "cpp",
        "telemetry.sdk.name": "envoy",
        "telemetry.sdk.version": "6aa1dcf8663b46421a2b73b8c357c20769600e53/1.34.10/Clean/RELEASE/BoringSSL"
      },
      "spanId": "0991001b62039324",
      "startTime": "2025-12-22T01:11:02.257178Z",
      "status": {
        "code": "Unset",
        "message": ""
      },
      "@timestamp": "0001-01-01T00:00:00Z",
      "traceId": "69af90a71e3c9c849c12771789b860e6",
      "traceState": ""
    },
    "sort": [
      1766365872259
    ]
  },
  {
    "_index": "otel-traces-2025-12-22",
    "_id": "5E-cQ5sBmc08HMcQPz9A",
    "_score": null,
    "_source": {
      "attributes": {
        "data_stream": {
          "dataset": "default",
          "namespace": "namespace",
          "type": "span"
        },
        "http.flavor": "1.1",
        "http.method": "GET",
        "http.request_content_length": 0,
        "http.response_content_length": 100,
        "http.route": "/status",
        "http.scheme": "http",
        "http.status_code": 200,
        "http.target": "/status",
        "http.user_agent": "Go-http-client/1.1",
        "net.host.name": "_",
        "net.host.port": 8081,
        "net.sock.peer.addr": "172.22.0.27",
        "net.sock.peer.port": 55298
      },
      "droppedAttributesCount": 0,
      "droppedEventsCount": 0,
      "droppedLinksCount": 0,
      "endTime": "2025-12-22T01:11:10.533Z",
      "instrumentationScope": {
        "droppedAttributesCount": 0,
        "name": "nginx",
        "schemaUrl": "",
        "version": "1.29.0"
      },
      "kind": "Server",
      "name": "image-provider",
      "parentSpanId": "",
      "resource": {
        "host.name": "d2d8144cbe33",
        "os.type": "linux",
        "service.name": "image-provider"
      },
      "spanId": "c5ad9933e672d348",
      "startTime": "2025-12-22T01:11:10.533Z",
      "status": {
        "code": "Unset",
        "message": ""
      },
      "@timestamp": "0001-01-01T00:00:00Z",
      "traceId": "53fe9229c2a6335a8f1bf9341c68b256",
      "traceState": ""
    },
    "sort": [
      1766365870533
    ]
  }
]